catus/__init__.py
catus-0.0.6.dist-info/LICENSE
catus-0.0.6.dist-info/METADATA
catus-0.0.6.dist-info/WHEEL
catus-0.0.6.dist-info/top_level.txt
catus-0.0.6.dist-info/RECORD
