Metadata-Version: 2.1
Name: catus
Version: 0.0.6
Summary: catus
Home-page: https://github.com/mdmould/catus
Author: Matthew Mould
Author-email: mattdmould@gmail.com
License: MIT
Requires-Python: >=3.7
License-File: LICENSE
Requires-Dist: numpy
Requires-Dist: matplotlib
Requires-Dist: kaydee
